LICENSE
MANIFEST.in
README.rst
setup.py
wAuth/__init__.py
wAuth/admin.py
wAuth/apps.py
wAuth/models.py
wAuth/tests.py
wAuth/urls.py
wAuth/views.py
wAuth/wsettings.py
wAuth/migrations/__init__.py
wAuth/templates/wlogged.html
wAuth/templates/wlogin.html
wixot_auth.egg-info/PKG-INFO
wixot_auth.egg-info/SOURCES.txt
wixot_auth.egg-info/dependency_links.txt
wixot_auth.egg-info/requires.txt
wixot_auth.egg-info/top_level.txt